MANIFEST.in
README.md
setup.py
geog/__init__.py
geog/geog.py
geog.egg-info/PKG-INFO
geog.egg-info/SOURCES.txt
geog.egg-info/dependency_links.txt
geog.egg-info/not-zip-safe
geog.egg-info/requires.txt
geog.egg-info/top_level.txt