Metadata-Version: 1.0
Name: geog
Version: 0.0.2
Summary: Numpy-based vectorized geospatial functions
Home-page: https://github.com/jwass/geog
Author: Jacob Wasserman
Author-email: jwasserman@gmail.com
License: MIT
Platform: UNKNOWN
